{
	"pages": [ //pages数组中第一项表示应用启动页，参考：https://uniapp.dcloud.io/collocation/pages
		{
			"path": "pages/index/index",
			"style": {
				"navigationBarTitleText": "uni-app",
				"navigationStyle": "custom"
			}
		},
		{
			"path": "pages/index/login",
			"style": {
				"navigationBarTitleText": "uni-app",
				"navigationStyle": "custom"
			}
		},
		{
			"path": "pages/index/my",
			"style": {
				"navigationBarTitleText": "uni-app",
				"navigationStyle": "custom"
			}
		},
		{
			"path": "pages/index/city",
			"style": {
				"navigationBarTitleText": "uni-app",
				"navigationStyle": "custom"
			}
		},
		{
			"path": "pages/index/search",
			"style": {
				"navigationBarTitleText": "uni-app",
				"navigationStyle": "custom"
			}
		},
		{
			"path": "pages/index/bookdetail",
			"style": {
				"navigationBarTitleText": "uni-app",
				"navigationStyle": "custom"
			}
		},
		{
			"path": "pages/index/list",
			"style": {
				"navigationBarTitleText": "uni-app",
				"navigationStyle": "custom"
			}
		},
		{
			"path": "pages/index/presslist",
			"style": {
				"navigationBarTitleText": "uni-app",
				"navigationStyle": "custom"
			}
		},
		{
			"path": "pages/index/comic",
			"style": {
				"navigationBarTitleText": "uni-app",
				"navigationStyle": "custom"
			}
		},
		{
			"path": "pages/index/register",
			"style": {
				"navigationBarTitleText": "uni-app",
				"navigationStyle": "custom"
			}
		},
		{
			"path": "pages/my/setting",
			"style": {
				"navigationBarTitleText": "uni-app",
				"navigationStyle": "custom"
			}
		},
		{
			"path": "pages/my/browse",
			"style": {
				"navigationBarTitleText": "uni-app",
				"navigationStyle": "custom"
			}
		},
		{
			"path": "pages/index/test",
			"style": {
				"navigationBarTitleText": "uni-app",
				"navigationStyle": "custom"
			}
		}
	],
	"globalStyle": {
		"navigationBarTextStyle": "black",
		"navigationBarTitleText": "uni-app",
		"navigationBarBackgroundColor": "#F8F8F8",
		"backgroundColor": "#F8F8F8"
	}
}
